{
  "doc_id": "asn-feather-parts-reattach",
  "organism_common": "Birds",
  "strategy_summary": "Birds, the masters of the skies, have feathers that are marvels of nature’s engineering. These feathers not only provide warmth and waterproofing but also enable these majestic animals to show us the miracle of flight.",
  "mechanism": "Each feather features a central shaft, or rachis, lined with filaments called barbs, which are fringed with tinier filaments known as barbules. In downy feathers, this arrangement traps air, creating superb insulation. Flight feathers, however, have barbules that hook onto each other, much like a zipper, forming a continuous vane—crucial for aerodynamic efficiency. Each barbule hosts hundreds of these hooks, with millions present in a single feather. When feathers become ruffled, birds meticulously preen and comb, running their beaks through their plumage to re-engage these hooks. This natural grooming process ensures that their feathers remain perfectly aligned and functional, maintaining their ability to insulate and support flight.\n\nInspired by this natural design, we can envision advanced textiles that mimic the feather’s interlocking system, offering superior insulation and durability. In aerospace engineering, materials emulating this hook structure could enhance the strength and flexibility of aircraft components. Everyday fasteners and closures could also benefit, becoming more efficient and easy to repair. By looking to the skies and the feathers that lift birds, we can create innovations that are both practical and harmoniously aligned with nature’s wisdom down here on the ground.\n\nThis page was produced in part with the assistance of AI, which is allowing us to greatly expand the volume of content available on AskNature. All of the content has been reviewed for accuracy and appropriateness by human editors. To provide feedback or to get involved with the project, contact us .",
  "function_addressed": [
    "attach temporarily"
  ],
  "function_keys": [
    "attach::temporarily"
  ],
  "subgroup_keys": [
    "attach"
  ],
  "source_url": "https://asknature.org/strategy/feather-parts-reattach/",
  "keywords": [
    "nature",
    "ingenious",
    "velcro",
    "interlocking",
    "feather",
    "hooks"
  ],
  "provenance": "fetched"
}